setup.py
django_migreme.egg-info/PKG-INFO
django_migreme.egg-info/SOURCES.txt
django_migreme.egg-info/dependency_links.txt
django_migreme.egg-info/top_level.txt
migreme/__init__.py
migreme/models.py
migreme/tests.py
migreme/views.py