Metadata-Version: 1.1
Name: django-migreme
Version: 0.0.1
Summary: Django Migre.me app
Home-page: https://github.com/TracyWebTech/django-migreme
Author: Tracy Web Technologies
Author-email: contato@tracy.com.br
License: BSD
Download-URL: https://github.com/TracyWebTech/django-migreme/downloads
Keywords: django apps migreme migre.me
Platform: UNKNOWN
Classifier: Environment :: Plugins
Classifier: Framework :: Django
Classifier: Intended Audience :: Developers
Classifier: License :: OSI Approved :: BSD License
Classifier: Operating System :: OS Independent
Classifier: Programming Language :: Python
Classifier: Topic :: Software Development :: Libraries :: Python Modules
